pyrpd/__init__.py
pyrpd/_pyrpd.cp314-win_amd64.pyd
pyrpd/tests/__init__.py
pyrpd/tests/wechat.py
pyrpd/tests/weixin.py
pyrpd/tests/wxwork.py
pyrpd-1.0.6.dist-info/licenses/LICENSE
pyrpd-1.0.6.dist-info/METADATA
pyrpd-1.0.6.dist-info/WHEEL
pyrpd-1.0.6.dist-info/top_level.txt
pyrpd-1.0.6.dist-info/RECORD
