Metadata-Version: 2.4
Name: pyrpd
Version: 1.0.6
Summary: Invoke remote functions by python.
Home-page: https://github.com/ljc545w/pyrpd
Author-email: Jack Li <ljc545w@qq.com>
License-Expression: MIT
Project-URL: Homepage, https://github.com/ljc545w/pyrpd
Keywords: remote ipc,debug
Platform: win
Classifier: Development Status :: 3 - Alpha
Classifier: Intended Audience :: Developers
Classifier: Programming Language :: Python :: 3
Classifier: Programming Language :: Python
Requires-Python: >=3.8
License-File: LICENSE
Dynamic: license-file
Dynamic: platform
